JaxSSO/SSO_model.py
JaxSSO/__init__.py
JaxSSO/assemblemodel.py
JaxSSO/element.py
JaxSSO/model.py
JaxSSO/optimization.py
JaxSSO/solver.py
jaxsso-1.0.1.dist-info/LICENSE.txt
jaxsso-1.0.1.dist-info/METADATA
jaxsso-1.0.1.dist-info/WHEEL
jaxsso-1.0.1.dist-info/top_level.txt
jaxsso-1.0.1.dist-info/RECORD
