Metadata-Version: 2.1
Name: jaxsso
Version: 1.0.1
Summary: A framework for structural shape optimization based on automatic differentiation (AD) and the adjoint method, enabled by JAX
Home-page: https://github.com/GaoyuanWu/JaxSSO
Author: Gaoyuan Wu
Author-email: gaoyuanw@princeton.edu
Keywords: jax,automatic differentiation,shape optimization,finite element analysis,form finding,topology optimization,structural optimization
Classifier: License :: OSI Approved :: MIT License
Classifier: Programming Language :: Python :: 3
Classifier: Programming Language :: Python :: 3.7
Classifier: Programming Language :: Python :: 3.8
Classifier: Programming Language :: Python :: 3.9
Classifier: Programming Language :: Python :: 3.10
Classifier: Programming Language :: Python :: 3.11
Classifier: Programming Language :: Python :: 3.12
Requires-Python: >=3.7
License-File: LICENSE.txt
Requires-Dist: numpy >=1.22.0
Requires-Dist: matplotlib
Requires-Dist: jax >=0.4.24
Requires-Dist: scipy
